[
    {
        "name": "Hotel Polo Towers Agartala",
        "pics": [
            "https://lh5.googleusercontent.com/p/AF1QipMFyyXSzCKmX-jl3b08cF5OkDpjDCDp_G1scTuF=s296-w296-h168-n-k-no-v1",
            "https://lh5.googleusercontent.com/p/AF1QipPKFVxYolq2sKAuAU3SAJc2RtnCrILZePJXVQcC=s296-w296-h168-n-k-no-v1",
            "https://lh5.googleusercontent.com/p/AF1QipNujSTKhEn8Vtvg8jWEcU9M9jrQuKisbTZOEVxD=s296-w296-h168-n-k-no-v1",
            "https://lh5.googleusercontent.com/p/AF1QipMJ3-EM-OZOTy-Z_zt6z5Y9ZRtHa39qUQdi17sC=s296-w296-h168-n-k-no-v1"
        ],
        "review_star": "4.5",
        "review_count": "(3,650)",
        "amenities_short": [
            "Free breakfast",
            "Free Wi-Fi",
            "Free parking",
            "Pool",
            "Air conditioning",
            "Spa",
            "Restaurant",
            "Room service"
        ],
        "link": "https://www.google.com/travel/hotels/entity/ChoI9MT2s9-onoefARoNL2cvMTFoX3Z2eTNyZhAB?q=hotels+in+Agartala+Tripura+India&ts=CAESCgoCCAMKAggDEAAaUwo1EjEyJTB4Mzc1M2Y0MGRjOTQxMjNhNzoweGQwYTEyNjNjNmM0MGM4Yzc6CEFnYXJ0YWxhGgASGhIUCgcI6A8QCBgQEgcI6A8QCBgRGAEyAggCKhMKDQoBIxIDAwQFOgNJTlIaACgI&ictx=3&rp=OAFIAg&ap=KigKEgmA4sIsebU3QBHiiSB-GM1WQBISCW296UBN_jdAEeKJIB5v1lZAMAE&ei=5TSqZqbWEYDOmsMP8eeT8Qs&sa=X&ved=2ahUKEwjm3P6sqtGHAxUAp2YCHfHzJL4QyvcEegQIBBAs",
        "description": "Across the street from Rabindra Kanan Park, this grand hotel is 2 km from Ujjayanta Palace and 11 km from Akhaura Junction railway station.<br/>Airy, polished rooms provide TVs, minifridges, and tea and coffeemaking facilities, in addition to Wi-Fi. Room service is available 24/7.<br/>Dining options include a traditional restaurant and an open-air BBQ eatery. Other amenities include a sleek bar, an indoor pool and a spa, as well as a gym, breakfast and parking.",
        "address": "VIP Rd, Kunjaban, Agartala, Tripura 799006",
        "phone": "0381 231 0110",
        "amenities": {
            "Internet": [
                "Wi-Fifree"
            ],
            "Services": [
                "Front desk24 hour",
                "Full-service laundry"
            ],
            "Parking & transportation": [
                "Parkingfree",
                "Valet parking",
                "Airport shuttle",
                "Local shuttle"
            ],
            "Accessibility": [
                "Accessible"
            ],
            "Food & drink": [
                "Restaurant",
                "Room service",
                "BreakfastfreeShow detailsBegin your first day at Agartala with a scrumptious buffet breakfast at Hotel Polo Towers, Agartala.\u00a0https://www.hotelpolotowers.com/...Holiday in Agartala | Hotel Polo Towers Agartala | Agartala Tour",
                "Breakfast buffet"
            ],
            "Pools": [
                "Pool"
            ],
            "Wellness": [
                "Spa"
            ],
            "Rooms": [
                "Air conditioning",
                "Kitchen"
            ]
        }
    },
    {
        "name": "A India Guest House - Best| Top Hotel| Guest House In Agartala Airport Area| Near Agartala",
        "pics": [
            "https://lh5.googleusercontent.com/p/AF1QipMrAVpqatJZtMxaQiVfTqPQ6pVcPfEUH7ef9Sjt=s296-w296-h168-n-k-no-v1",
            "https://lh5.googleusercontent.com/p/AF1QipMbKgaBLwDTulfLp_Bl6927HVWlmgwq4R9lU9u7=s296-w296-h168-n-k-no-v1",
            "https://lh4.googleusercontent.com/proxy/FzjxacPk41furLpD_0N48FqFLveY195bIfychvwF_NC_uvSXz_sY0klq3GQwr75eXtTSEivZKMJ5EwmgiFpdmqV7A4ViJbht5X4Wxt_nhx6RfaEZuMNb25wb60mLD-WHAyAxIMCD7IyM_cVp4nZ8JPPYtvRfklw=s296-w296-h168-n-k-no-v1",
            "https://lh5.googleusercontent.com/p/AF1QipPWsRuXoS6vY8EXruF-0x0GFMsDPgk9mB6y2_kT=s296-w296-h168-n-k-no-v1"
        ],
        "review_star": "4.4",
        "review_count": "(426)",
        "amenities_short": [
            "Free breakfast",
            "Free Wi-Fi",
            "Parking",
            "Pool",
            "Air conditioning",
            "Restaurant",
            "Room service",
            "Kitchen in some rooms"
        ],
        "link": "https://www.google.com/travel/hotels/entity/ChkIsIOC9enK48A6Gg0vZy8xMWYzanE0dDBnEAE?q=hotels+in+Agartala+Tripura+India&ts=CAESCgoCCAMKAggDEAAaUwo1EjEyJTB4Mzc1M2Y0MGRjOTQxMjNhNzoweGQwYTEyNjNjNmM0MGM4Yzc6CEFnYXJ0YWxhGgASGhIUCgcI6A8QCBgQEgcI6A8QCBgRGAEyAggCKhMKDQoBIxIDAwQFOgNJTlIaACgI&ictx=3&rp=OAFIAg&ap=KigKEgmA4sIsebU3QBHiiSB-GM1WQBISCW296UBN_jdAEeKJIB5v1lZAMAE&ei=5TSqZqbWEYDOmsMP8eeT8Qs&sa=X&ved=2ahUKEwjm3P6sqtGHAxUAp2YCHfHzJL4QyvcEegQIBBBC",
        "description": "",
        "address": "PTC Road, Narsingarh, Agartala, Tripura 799015",
        "phone": "093661 86768",
        "amenities": {
            "Internet": [
                "Wi-Fifree"
            ],
            "Services": [
                "Front desk24 hour",
                "Baggage storage",
                "Full-service laundry",
                "Wake up calls",
                "Housekeepingdaily"
            ],
            "Pools": [
                "Pool",
                "No hot tub"
            ],
            "Wellness": [
                "No fitness center",
                "No spa"
            ],
            "Languages spoken": [
                "English",
                "Hindi"
            ],
            "Bathrooms": [
                "Private bathroom",
                "Shower"
            ],
            "Food & drink": [
                "Restaurant",
                "Room service",
                "Breakfastfree"
            ],
            "Children": [
                "Kid-friendly"
            ],
            "Parking & transportation": [
                "Parking",
                "Airport shuttleextra charge",
                "Local shuttle"
            ],
            "Pets": [
                "No pets"
            ],
            "Rooms": [
                "Air conditioning in some rooms",
                "Kitchen in some rooms"
            ]
        }
    },
    {
        "name": "Hotel Welcome Palace",
        "pics": [
            "https://lh5.googleusercontent.com/p/AF1QipO1vuO82kGGzgzM6BKATWcnYPR6F9qpwcUOsCP0=s296-w296-h168-n-k-no-v1",
            "https://lh5.googleusercontent.com/p/AF1QipM0iIywVSfYMy8rNsMUtWG2CKyx6Tu0D77_HbFx=s296-w296-h168-n-k-no-v1",
            "https://lh3.googleusercontent.com/proxy/UcGXwlz9lwT1crhXuVCWP6cswXoaEekeF3mFsLWOxYbxE09GP3BBRY8HFKMZn-p0T2mOoLtMS40xXBfnb0SSk3KlX-Jzc6WbbULGPe4Xa5NFiDdZafsdzZkiRkKvQSNoRbbeIF0AZ8HiVoEJY6BXnei9at07RQ=s296-w296-h168-n-k-no-v1",
            "https://lh5.googleusercontent.com/p/AF1QipN1chpBbox0gmuqOWo-ppq88B9xnqPz4TcK4aiV=s296-w296-h168-n-k-no-v1"
        ],
        "review_star": "3.8",
        "review_count": "(1,425)",
        "amenities_short": [
            "Free breakfast",
            "Free Wi-Fi",
            "Air conditioning",
            "Restaurant",
            "Room service",
            "Airport shuttle",
            "Full-service laundry",
            "Kid-friendly"
        ],
        "link": "https://www.google.com/travel/hotels/entity/ChgI4an_i7-hnuGPARoLL2cvMXRocTg2bjIQAQ?q=hotels+in+Agartala+Tripura+India&ts=CAESCgoCCAMKAggDEAAaUwo1EjEyJTB4Mzc1M2Y0MGRjOTQxMjNhNzoweGQwYTEyNjNjNmM0MGM4Yzc6CEFnYXJ0YWxhGgASGhIUCgcI6A8QCBgQEgcI6A8QCBgRGAEyAggCKhMKDQoBIxIDAwQFOgNJTlIaACgI&ictx=3&rp=OAFIAg&ap=KigKEgmA4sIsebU3QBHiiSB-GM1WQBISCW296UBN_jdAEeKJIB5v1lZAMAE&ei=5TSqZqbWEYDOmsMP8eeT8Qs&sa=X&ved=2ahUKEwjm3P6sqtGHAxUAp2YCHfHzJL4QyvcEegQIBBBg",
        "description": "Along a bustling thoroughfare with shops and businesses, this modest hotel is 2 km from Ujjayanta Palace, a former royal residence now housing the Tripura State Museum. It's 5 km from Agartala train station.<br/>Warmly furnished, unpretentious rooms come with Wi-Fi access and TVs. Upgraded rooms feature sitting areas. Room service is available.<br/>A down-to-earth restaurant serves Thai, Chinese and local cuisine. There's a doctor on-call.",
        "address": "Hari Ganga Basak Road, Post Office Chowmuhani, Agartala, Tripura 799001",
        "phone": "0381 238 0101",
        "amenities": {
            "Internet": [
                "Wi-Fifree"
            ],
            "Services": [
                "Front desk24 hour",
                "Full-service laundry"
            ],
            "Pools": [
                "No hot tub"
            ],
            "Wellness": [
                "No fitness center",
                "No spa"
            ],
            "Rooms": [
                "Air conditioning"
            ],
            "Food & drink": [
                "Restaurant",
                "Room service",
                "Breakfastfree"
            ],
            "Children": [
                "Kid-friendly"
            ],
            "Parking & transportation": [
                "Airport shuttleextra charge",
                "Local shuttle"
            ],
            "Pets": [
                "No pets"
            ]
        }
    },
    {
        "name": "Hotel Woodland Park",
        "pics": [
            "https://lh5.googleusercontent.com/p/AF1QipPN7WgeVY93HZZRtz6I4Dwe8gVKcpZM_GBQO3rd=s296-w296-h168-n-k-no-v1",
            "https://lh5.googleusercontent.com/p/AF1QipNj5h5qW4ArMpDD1dCCqG3e6q52p1ucXw7pUGDQ=s296-w296-h168-n-k-no-v1",
            "https://lh5.googleusercontent.com/p/AF1QipNb4SjmMzGQ0rW1ysojxMoWlojde67HprgX1J9U=s296-w296-h168-n-k-no-v1",
            "https://lh5.googleusercontent.com/p/AF1QipMfKL9sM93uSfGAkvieKtvuZRba0RnLakHLCpr7=s296-w296-h168-n-k-no-v1"
        ],
        "review_star": "3.6",
        "review_count": "(1,257)",
        "amenities_short": [
            "Free breakfast",
            "Free Wi-Fi",
            "Free parking",
            "Air conditioning",
            "Restaurant",
            "Room service",
            "Airport shuttle",
            "Full-service laundry"
        ],
        "link": "https://www.google.com/travel/hotels/entity/ChgIqs3StsrBl7gLGgwvZy8xamdseXk0NjQQAQ?q=hotels+in+Agartala+Tripura+India&ts=CAESCgoCCAMKAggDEAAaUwo1EjEyJTB4Mzc1M2Y0MGRjOTQxMjNhNzoweGQwYTEyNjNjNmM0MGM4Yzc6CEFnYXJ0YWxhGgASGhIUCgcI6A8QCBgQEgcI6A8QCBgRGAEyAggCKhMKDQoBIxIDAwQFOgNJTlIaACgI&ictx=3&rp=OAFIAg&ap=KigKEgmA4sIsebU3QBHiiSB-GM1WQBISCW296UBN_jdAEeKJIB5v1lZAMAE&ei=5TSqZqbWEYDOmsMP8eeT8Qs&sa=X&ved=2ahUKEwjm3P6sqtGHAxUAp2YCHfHzJL4QyvcEegQIBBB7",
        "description": "Set in a bustling area with shops and businesses, this modest budget hotel is 18 minutes' walk from local history at the Tripura Government Museum and 4 km from National Highway 8.<br/>Straightforward rooms feature flat-screen TVs, minifridges, and/or tea and coffeemaking facilities, in addition to en suite bathrooms with bucket baths; some add sitting areas. Room service is available 24/7.<br/>There's a casual restaurant.",
        "address": "Math Chowmuhani, Jail Ashram Rd, Shiv Nagar, Indranagar, Agartala, Tripura 799001",
        "phone": "097745 85708",
        "amenities": {
            "Internet": [
                "Wi-Fifree"
            ],
            "Services": [
                "Front desk24 hour",
                "Full-service laundry"
            ],
            "Pools": [
                "No pools",
                "No hot tub"
            ],
            "Wellness": [
                "No fitness center",
                "No spa"
            ],
            "Pets": [
                "No pets"
            ],
            "Food & drink": [
                "Restaurant",
                "Room service",
                "Breakfastfree"
            ],
            "Children": [
                "Kid-friendly"
            ],
            "Parking & transportation": [
                "Parkingfree",
                "Airport shuttleextra charge",
                "Local shuttle"
            ],
            "Accessibility": [
                "Accessible"
            ],
            "Rooms": [
                "Air conditioning"
            ]
        }
    },
    {
        "name": "Hotel Rimi International",
        "pics": [
            "https://lh5.googleusercontent.com/p/AF1QipOHekES2FtzdtqGMFm-GPnZo6tB3mC2-iPMJx6Q=s296-w296-h168-n-k-no-v1",
            "https://lh5.googleusercontent.com/p/AF1QipNbVSJeciutvMYpAMvEOkQM-ULQjdPSdo6X-Jcw=s296-w296-h168-n-k-no-v1",
            "https://lh5.googleusercontent.com/p/AF1QipMEAMGKNS1R8DvFoVZ98hOAd0qOlSnde-Iad2bN=s296-w296-h168-n-k-no-v1",
            "https://lh5.googleusercontent.com/p/AF1QipNacA8jTvqghifGTZomxJb-vdMdE5gzGSGOxAW6=s296-w296-h168-n-k-no-v1"
        ],
        "review_star": "4.5",
        "review_count": "(907)",
        "amenities_short": [
            "Free breakfast",
            "Free Wi-Fi",
            "Free parking",
            "Pool",
            "Air conditioning",
            "Restaurant",
            "Room service",
            "Full-service laundry"
        ],
        "link": "https://www.google.com/travel/hotels/entity/ChoIzJPL4oC96JezARoNL2cvMTFyd2xwYjlidxAB?q=hotels+in+Agartala+Tripura+India&ts=CAESCgoCCAMKAggDEAAaUwo1EjEyJTB4Mzc1M2Y0MGRjOTQxMjNhNzoweGQwYTEyNjNjNmM0MGM4Yzc6CEFnYXJ0YWxhGgASGhIUCgcI6A8QCBgQEgcI6A8QCBgRGAEyAggCKhMKDQoBIxIDAwQFOgNJTlIaACgI&ictx=3&rp=OAFIAg&ap=KigKEgmA4sIsebU3QBHiiSB-GM1WQBISCW296UBN_jdAEeKJIB5v1lZAMAE&ei=5TSqZqbWEYDOmsMP8eeT8Qs&sa=X&ved=2ahUKEwjm3P6sqtGHAxUAp2YCHfHzJL4QyvcEegUIBBCWAQ",
        "description": "Set among apartment buildings, this laid-back hotel with a glass facade is 1 km from Ujjayanta Palace, 3 km from Nehru Park and 4 km from Jogendranagar train station.<br/>The understated rooms provide TVs, Wi-Fi and minifridges. Room service is available.<br/>An unassuming restaurant serves international cuisine and features a bar. Other amenities include conference space, parking and breakfast.",
        "address": "Maharaja Bir Bikram Sarani, Shiv Nagar, Dhaleswar, Agartala, Tripura 799007",
        "phone": "069093 12300",
        "amenities": {
            "Internet": [
                "Wi-Fifree"
            ],
            "Services": [
                "Front desk24 hour",
                "Full-service laundry"
            ],
            "Parking & transportation": [
                "Parkingfree",
                "Valet parking",
                "Local shuttle"
            ],
            "Rooms": [
                "Air conditioning"
            ],
            "Food & drink": [
                "Restaurant",
                "Room service",
                "Breakfastfree"
            ],
            "Pools": [
                "Pool",
                "No hot tub"
            ],
            "Wellness": [
                "No fitness center"
            ]
        }
    },
    {
        "name": "Hotel Anurag Palace",
        "pics": [
            "https://lh5.googleusercontent.com/p/AF1QipPfjB7Gue3TYSKDPorSVZQhEjOD4D7v_sHa4B1F=s296-w296-h168-n-k-no-v1",
            "https://lh5.googleusercontent.com/p/AF1QipMVY2d8ZtsSm0W5fn6b1tKqSbLfat3dP_DYMUeO=s296-w296-h168-n-k-no-v1",
            "https://lh5.googleusercontent.com/p/AF1QipN0oDw-4ClcpQh-tsIH0mPEHTRX-4N9I8IQ0QWo=s296-w296-h168-n-k-no-v1",
            "https://lh5.googleusercontent.com/p/AF1QipMHZ7GC1Q5PZm7jZJFyx_BUG9063PLv_5F0sXFO=s296-w296-h168-n-k-no-v1"
        ],
        "review_star": "3.7",
        "review_count": "(172)",
        "amenities_short": [
            "Breakfast ($)",
            "Free Wi-Fi",
            "Air conditioning",
            "Room service",
            "Full-service laundry",
            "Business center"
        ],
        "link": "https://www.google.com/travel/hotels/entity/ChkIg92Mnp3a4MxuGg0vZy8xMW43djdua242EAE?q=hotels+in+Agartala+Tripura+India&ts=CAESCgoCCAMKAggDEAAaUwo1EjEyJTB4Mzc1M2Y0MGRjOTQxMjNhNzoweGQwYTEyNjNjNmM0MGM4Yzc6CEFnYXJ0YWxhGgASGhIUCgcI6A8QCBgQEgcI6A8QCBgRGAEyAggCKhMKDQoBIxIDAwQFOgNJTlIaACgI&ictx=3&rp=OAFIAg&ap=KigKEgmA4sIsebU3QBHiiSB-GM1WQBISCW296UBN_jdAEeKJIB5v1lZAMAE&ei=5TSqZqbWEYDOmsMP8eeT8Qs&sa=X&ved=2ahUKEwjm3P6sqtGHAxUAp2YCHfHzJL4QyvcEegUIBBCtAQ",
        "description": "Set among shops and businesses, this low-key hotel is 2 km from Dimsagar Lake Park, 3 km from Indranagar Kalibari temple and 5 km from the NH8 road.<br/>Featuring colourful furnishings, the compact, relaxed rooms provide Wi-Fi, ceiling fans and TVs, as well as kettles, and en suite bathrooms with bucket baths. Some upgraded rooms add air conditioning.<br/>Parking and breakfast are available.",
        "address": "Icici bank, Alongside, Old, Motor Stand Rd, near Motorstand BOC, Agartala, Tripura 799001",
        "phone": "070050 21987",
        "amenities": {
            "Internet": [
                "Wi-Fifree"
            ],
            "Services": [
                "Front desk24 hour",
                "Full-service laundry",
                "Elevator",
                "Housekeepingdaily"
            ],
            "Parking & transportation": [
                "Transfer",
                "Local shuttle"
            ],
            "Business & events": [
                "Business center",
                "Meeting rooms"
            ],
            "Rooms": [
                "Air conditioning in some rooms",
                "Refrigerator in some rooms"
            ],
            "Food & drink": [
                "Room service",
                "Breakfastextra charge"
            ],
            "Pools": [
                "No pools",
                "No hot tub"
            ],
            "Wellness": [
                "No fitness center",
                "No spa"
            ],
            "Languages spoken": [
                "English",
                "Hindi"
            ],
            "Bathrooms": [
                "Private bathroom",
                "Shower"
            ]
        }
    },
    {
        "name": "Hotel Haven Intercontinental",
        "pics": [
            "https://lh5.googleusercontent.com/p/AF1QipNOozxF0x3il3GzD1civB5P8j_4Xi4yKSOwpv-U=s296-w296-h168-n-k-no-v1",
            "https://lh5.googleusercontent.com/p/AF1QipO8AT1s-TWCWZXLxuuzPECMC2j9PqOQM6DzYUWB=s296-w296-h168-n-k-no-v1",
            "https://lh5.googleusercontent.com/p/AF1QipPFEtLUvlcIyT1raiSduWZRRMp56wXdXmVB2Aeg=s296-w296-h168-n-k-no-v1",
            "https://lh5.googleusercontent.com/p/AF1QipMrvlUyDr9ehGvA4zU9uMT1UZ4hAu4_P8FsLEIl=s296-w296-h168-n-k-no-v1"
        ],
        "review_star": "3.9",
        "review_count": "(825)",
        "amenities_short": [
            "Free breakfast",
            "Free Wi-Fi",
            "Free parking",
            "Air conditioning",
            "Restaurant",
            "Room service",
            "Kitchen in some rooms",
            "Full-service laundry",
            "Kid-friendly"
        ],
        "link": "https://www.google.com/travel/hotels/entity/ChoIusjO8_fKse7ZARoNL2cvMTFjMmo3aHY2YxAB?q=hotels+in+Agartala+Tripura+India&ts=CAESCgoCCAMKAggDEAAaUwo1EjEyJTB4Mzc1M2Y0MGRjOTQxMjNhNzoweGQwYTEyNjNjNmM0MGM4Yzc6CEFnYXJ0YWxhGgASGhIUCgcI6A8QCBgQEgcI6A8QCBgRGAEyAggCKhMKDQoBIxIDAwQFOgNJTlIaACgI&ictx=3&rp=OAFIAg&ap=KigKEgmA4sIsebU3QBHiiSB-GM1WQBISCW296UBN_jdAEeKJIB5v1lZAMAE&ei=5TSqZqbWEYDOmsMP8eeT8Qs&sa=X&ved=2ahUKEwjm3P6sqtGHAxUAp2YCHfHzJL4QyvcEegUIBBDEAQ",
        "description": "",
        "address": "Sakuntala Rd, Madhyapara, metrobazar, Agartala, Tripura 799010",
        "phone": "0381 238 4838",
        "amenities": {
            "Internet": [
                "Wi-Fifree"
            ],
            "Services": [
                "Front desk24 hour",
                "Full-service laundry"
            ],
            "Pools": [
                "No hot tub"
            ],
            "Wellness": [
                "No fitness center",
                "No spa"
            ],
            "Rooms": [
                "Air conditioning",
                "Kitchen in some rooms"
            ],
            "Food & drink": [
                "Restaurant",
                "Room service",
                "Breakfastfree"
            ],
            "Children": [
                "Kid-friendly"
            ],
            "Parking & transportation": [
                "Parkingfree",
                "Transfer",
                "Local shuttle"
            ],
            "Pets": [
                "No pets"
            ]
        }
    },
    {
        "name": "Snehalata Homestay",
        "pics": [
            "https://lh5.googleusercontent.com/p/AF1QipMxwX7Epz1LjAqo2DPt2ny1SBFyMSx2OCV4tgCO=s296-w296-h168-n-k-no-v1",
            "https://lh5.googleusercontent.com/p/AF1QipOoa2tIcvhdKrXIwVve4y27Uha74VphmwfO6kso=s296-w296-h168-n-k-no-v1",
            "https://lh5.googleusercontent.com/p/AF1QipN8FnqZ4RiBpyZWMe02n4HhjxdktzvkAE3JVvXp=s296-w296-h168-n-k-no-v1",
            "https://lh5.googleusercontent.com/p/AF1QipNCjO2H-mqXAxXnvz6nJCtp1lSKIEZgOiQId2dE=s296-w296-h168-n-k-no-v1"
        ],
        "review_star": "4.6",
        "review_count": "(61)",
        "amenities_short": [
            "Free Wi-Fi",
            "Free parking",
            "Pool",
            "Air conditioning",
            "Kitchen in some rooms",
            "Full-service laundry",
            "Kid-friendly",
            "Smoke-free property"
        ],
        "link": "https://www.google.com/travel/hotels/entity/ChoI1fmPvra3k7SLARoNL2cvMTFuMTFzNDg5dhAB?q=hotels+in+Agartala+Tripura+India&ts=CAESCgoCCAMKAggDEAAaUwo1EjEyJTB4Mzc1M2Y0MGRjOTQxMjNhNzoweGQwYTEyNjNjNmM0MGM4Yzc6CEFnYXJ0YWxhGgASGhIUCgcI6A8QCBgQEgcI6A8QCBgRGAEyAggCKhMKDQoBIxIDAwQFOgNJTlIaACgI&ictx=3&rp=OAFIAg&ap=KigKEgmA4sIsebU3QBHiiSB-GM1WQBISCW296UBN_jdAEeKJIB5v1lZAMAE&ei=5TSqZqbWEYDOmsMP8eeT8Qs&sa=X&ved=2ahUKEwjm3P6sqtGHAxUAp2YCHfHzJL4QyvcEegUIBBDfAQ",
        "description": "",
        "address": "Jamaipara Road, Chandimata Club, Dukli, Agartala, Tripura 799003",
        "phone": "069093 69095",
        "amenities": {
            "Internet": [
                "Wi-Fifree"
            ],
            "Activities": [
                "Bicycle rentalextra charge"
            ],
            "Children": [
                "Kid-friendly"
            ],
            "Parking & transportation": [
                "Parkingfree",
                "Self parking",
                "Private car serviceextra charge"
            ],
            "Business & events": [
                "Meeting rooms"
            ],
            "Rooms": [
                "Air conditioning in some rooms",
                "Kitchen in some rooms",
                "Refrigerator in some rooms",
                "Microwave in some rooms",
                "Coffee maker in some rooms"
            ],
            "Policies & payments": [
                "Smoke-free property",
                "No credit cards",
                "NFC mobile payments",
                "Cash",
                "Checks"
            ],
            "Services": [
                "Front desk24 hour",
                "Baggage storage",
                "Full-service laundry",
                "Self-service laundry",
                "Housekeeping"
            ],
            "Pools": [
                "Pool",
                "No hot tub"
            ],
            "Wellness": [
                "No fitness center",
                "No spa"
            ],
            "Languages spoken": [
                "English",
                "Hindi"
            ],
            "Bathrooms": [
                "Private bathroom",
                "Shower"
            ]
        }
    },
    {
        "name": "Hotel Grandzuri",
        "pics": [
            "https://lh5.googleusercontent.com/p/AF1QipOwniFJX9qysLB4nv9XRx1UXlMn8fpatN-Nd4R8=s296-w296-h168-n-k-no-v1",
            "https://lh5.googleusercontent.com/p/AF1QipMTuz-MsATk2Dd1tJSATEggOvy8mlge82FRQUEi=s296-w296-h168-n-k-no-v1",
            "https://lh5.googleusercontent.com/p/AF1QipOaDRbp4ETr_Xa33bXpz272DSPMezrP5aO7BOUS=s296-w296-h168-n-k-no-v1",
            "https://lh5.googleusercontent.com/p/AF1QipOl-XAt4TjiMi_rSzhQE6QbqvANq_HM8XGBJNjc=s296-w296-h168-n-k-no-v1"
        ],
        "review_star": "3.5",
        "review_count": "(79)",
        "amenities_short": [
            "Free breakfast",
            "Free Wi-Fi",
            "Free parking",
            "Air conditioning",
            "Restaurant",
            "Room service",
            "Kitchen in some rooms",
            "Airport shuttle"
        ],
        "link": "https://www.google.com/travel/hotels/entity/ChoIn5i99J7t6tTAARoNL2cvMTFrcm1yMTJoNBAB?q=hotels+in+Agartala+Tripura+India&ts=CAESCgoCCAMKAggDEAAaUwo1EjEyJTB4Mzc1M2Y0MGRjOTQxMjNhNzoweGQwYTEyNjNjNmM0MGM4Yzc6CEFnYXJ0YWxhGgASGhIUCgcI6A8QCBgQEgcI6A8QCBgRGAEyAggCKhMKDQoBIxIDAwQFOgNJTlIaACgI&ictx=3&rp=OAFIAg&ap=KigKEgmA4sIsebU3QBHiiSB-GM1WQBISCW296UBN_jdAEeKJIB5v1lZAMAE&ei=5TSqZqbWEYDOmsMP8eeT8Qs&sa=X&ved=2ahUKEwjm3P6sqtGHAxUAp2YCHfHzJL4QyvcEegUIBBD2AQ",
        "description": "",
        "address": "Agartala Airport Rd, VIP Road, Usha Bazar, Agartala, Tripura 799009",
        "phone": "087319 94448",
        "amenities": {
            "Internet": [
                "Wi-Fifree",
                "Wi-Fi in public areas",
                "Public internet workstation"
            ],
            "Policies & payments": [
                "NFC mobile payments",
                "Cash"
            ],
            "Pools": [
                "No pools",
                "No hot tub"
            ],
            "Wellness": [
                "No fitness center",
                "No spa"
            ],
            "Business & events": [
                "Meeting rooms"
            ],
            "Languages spoken": [
                "English",
                "Hindi"
            ],
            "Bathrooms": [
                "Private bathroom",
                "Shower"
            ],
            "Food & drink": [
                "Restaurant",
                "Table service",
                "Buffet dinner",
                "Room service24 hour",
                "Breakfastfree",
                "Vending machines"
            ],
            "Services": [
                "Front desk24 hour",
                "Baggage storage",
                "Concierge",
                "Full-service laundry",
                "Elevator",
                "Wake up calls",
                "Housekeepingdaily",
                "Turndown service"
            ],
            "Parking & transportation": [
                "Parkingfree",
                "Self parkingfree",
                "Valet parkingfree",
                "Airport shuttleextra charge",
                "Private car serviceextra charge",
                "Car rental onsite",
                "Local shuttle"
            ],
            "Accessibility": [
                "Accessible",
                "Accessible parking",
                "Accessible elevator"
            ],
            "Pets": [
                "No pets"
            ],
            "Rooms": [
                "Air conditioning",
                "Kitchen in some rooms"
            ]
        }
    },
    {
        "name": "Prantik Hotel",
        "pics": [
            "https://lh5.googleusercontent.com/p/AF1QipO3u1B2MEkpEYoTqHmKKmWLiV26uwH-xxp8_Scv=s296-w296-h168-n-k-no-v1",
            "https://lh5.googleusercontent.com/p/AF1QipPorNuhOs9BWwvtYzWjF7e-xSPGDT4cXeWOEZVN=s296-w296-h168-n-k-no-v1",
            "https://lh4.googleusercontent.com/proxy/2MpLwO5NJm8tZswmVjHbK13MliX1Jq14oMIOFS44qVkp4EUCOaIsXOmTB_8p01bnPEedY46gH02m3bWPqwkVeq8BY4dW_gP3Ct9Q6FPFsuc9swTgW2vXRnYxy0OtMBmpGkawvz7qXNVEVUXdiHoCtHjymbWK7m8=s296-w296-h168-n-k-no-v1",
            "https://lh4.googleusercontent.com/proxy/SsEKUC2f7irGmRwzT2BedXd-aFSPMiuOMBIjTj0RO4dkzl_eV_gl79YACEitb5V3yTGKOOKMSU7oiVaF8xOXLtlgi07cW22UP9LdPn0-sld1B46m-4uzq6UDxb3-F4VRw09IdPTor7NHxy1w9iv27mDPh3j1tqA=s296-w296-h168-n-k-no-v1"
        ],
        "review_star": "3.1",
        "review_count": "(512)",
        "amenities_short": [
            "Free Wi-Fi",
            "Pool",
            "Air conditioning",
            "Airport shuttle",
            "Full-service laundry"
        ],
        "link": "https://www.google.com/travel/hotels/entity/ChkIj6Hf7c6YsNVeGg0vZy8xMWJ3Z3dkZmxoEAE?q=hotels+in+Agartala+Tripura+India&ts=CAESCgoCCAMKAggDEAAaUwo1EjEyJTB4Mzc1M2Y0MGRjOTQxMjNhNzoweGQwYTEyNjNjNmM0MGM4Yzc6CEFnYXJ0YWxhGgASGhIUCgcI6A8QCBgQEgcI6A8QCBgRGAEyAggCKhMKDQoBIxIDAwQFOgNJTlIaACgI&ictx=3&rp=OAFIAg&ap=KigKEgmA4sIsebU3QBHiiSB-GM1WQBISCW296UBN_jdAEeKJIB5v1lZAMAE&ei=5TSqZqbWEYDOmsMP8eeT8Qs&sa=X&ved=2ahUKEwjm3P6sqtGHAxUAp2YCHfHzJL4QyvcEegUIBBCRAg",
        "description": "",
        "address": "Prantik Hotel Netaji Subhash Road, opposite RCC, Agartala, Tripura 799001",
        "phone": "097741 30580",
        "amenities": {
            "Internet": [
                "Wi-Fifree"
            ],
            "Pools": [
                "Pool",
                "No hot tub"
            ],
            "Wellness": [
                "No fitness center",
                "No spa"
            ],
            "Services": [
                "Front desk24 hour",
                "Full-service laundry"
            ],
            "Parking & transportation": [
                "Airport shuttleextra charge",
                "Local shuttle"
            ],
            "Rooms": [
                "Air conditioning"
            ]
        }
    },
    {
        "name": "Veda Homestay",
        "pics": [
            "https://lh5.googleusercontent.com/p/AF1QipMenmNhIwuKA_mZMXdN7pHsy1iy3PU51Lq4odhG=s296-w296-h168-n-k-no-v1",
            "https://lh5.googleusercontent.com/p/AF1QipPnS5awbvy0yKZ3P6ZfM57ydU1i2a_6vQw1tISI=s296-w296-h168-n-k-no-v1",
            "https://lh5.googleusercontent.com/p/AF1QipNadoQKOVmTzRaepOcbQKLzyw4p6Pv1vsnXnyGT=s296-w296-h168-n-k-no-v1",
            "https://lh5.googleusercontent.com/p/AF1QipNBf22wIP4E-VZjqX0EaNj872EHjZe12h5W0cij=s296-w296-h168-n-k-no-v1"
        ],
        "review_star": "4.7",
        "review_count": "(52)",
        "amenities_short": [
            "Breakfast ($)",
            "Free Wi-Fi",
            "Kitchen in some rooms",
            "Full-service laundry",
            "Kid-friendly",
            "Smoke-free property"
        ],
        "link": "https://www.google.com/travel/hotels/entity/ChoIm6jbrJD58qv3ARoNL2cvMTF0cmRqMzVybRAB?q=hotels+in+Agartala+Tripura+India&ts=CAESCgoCCAMKAggDEAAaUwo1EjEyJTB4Mzc1M2Y0MGRjOTQxMjNhNzoweGQwYTEyNjNjNmM0MGM4Yzc6CEFnYXJ0YWxhGgASGhIUCgcI6A8QCBgQEgcI6A8QCBgRGAEyAggCKhMKDQoBIxIDAwQFOgNJTlIaACgI&ictx=3&rp=OAFIAg&ap=KigKEgmA4sIsebU3QBHiiSB-GM1WQBISCW296UBN_jdAEeKJIB5v1lZAMAE&ei=5TSqZqbWEYDOmsMP8eeT8Qs&sa=X&ved=2ahUKEwjm3P6sqtGHAxUAp2YCHfHzJL4QyvcEegUIBBCoAg",
        "description": "",
        "address": "SANKAR CHOWMANI, Krishna Nagar, Agartala, Tripura 799001",
        "phone": "098565 46269",
        "amenities": {
            "Internet": [
                "Wi-Fifree",
                "Wi-Fi in public areas"
            ],
            "Policies & payments": [
                "Smoke-free property",
                "No credit cards",
                "NFC mobile payments",
                "Cash"
            ],
            "Services": [
                "Baggage storage",
                "Concierge",
                "Convenience store",
                "Full-service laundry",
                "Self-service laundry",
                "Social hour",
                "Wake up calls",
                "Gift shop"
            ],
            "Pools": [
                "No pools",
                "No hot tub"
            ],
            "Languages spoken": [
                "English",
                "Hindi"
            ],
            "Food & drink": [
                "Breakfastextra charge"
            ],
            "Activities": [
                "Bicycle rentalextra charge",
                "Boutique shopping"
            ],
            "Children": [
                "Kid-friendly"
            ],
            "Wellness": [
                "No fitness center",
                "No spa"
            ],
            "Rooms": [
                "Kitchen"
            ]
        }
    },
    {
        "name": "Hotel Radha International",
        "pics": [
            "https://lh5.googleusercontent.com/p/AF1QipOevHintXrukAI4Ged96F5EYS62pwCZnFBCL__h=s296-w296-h168-n-k-no-v1",
            "https://lh5.googleusercontent.com/p/AF1QipPeirGWgL9dn32SMaY0DrH8883qslgrNWo8iss9=s296-w296-h168-n-k-no-v1",
            "https://lh5.googleusercontent.com/p/AF1QipO_nguEEpQDeatMPLuJtB7RUSY5tGok5L1ajHDc=s296-w296-h168-n-k-no-v1",
            "https://lh4.googleusercontent.com/proxy/0R43L2b7VA7kHD2HmX5UNskPScLHFkrpX3QSy3Z-gmkwG6qWJn0Oal6vZmKRKThQnRshk7XACdqQ-PAnZp-5ouy8LvgFlAY6Pf0NkwTMMnpD5udzMHWdc6ckUNxGUegim9MlP8vtHQfnXqdQSRIpDMVtYtxYmic=s296-w296-h168-n-k-no-v1"
        ],
        "review_star": "3.7",
        "review_count": "(367)",
        "amenities_short": [
            "Free breakfast",
            "Free Wi-Fi",
            "Pool",
            "Air conditioning",
            "Room service",
            "Full-service laundry",
            "Kid-friendly"
        ],
        "link": "https://www.google.com/travel/hotels/entity/ChkIxs2y3rW6ltfNARoML2cvMTI0dDNibnFuEAE?q=hotels+in+Agartala+Tripura+India&ts=CAESCgoCCAMKAggDEAAaUwo1EjEyJTB4Mzc1M2Y0MGRjOTQxMjNhNzoweGQwYTEyNjNjNmM0MGM4Yzc6CEFnYXJ0YWxhGgASGhIUCgcI6A8QCBgQEgcI6A8QCBgRGAEyAggCKhMKDQoBIxIDAwQFOgNJTlIaACgI&ictx=3&rp=OAFIAg&ap=KigKEgmA4sIsebU3QBHiiSB-GM1WQBISCW296UBN_jdAEeKJIB5v1lZAMAE&ei=5TSqZqbWEYDOmsMP8eeT8Qs&sa=X&ved=2ahUKEwjm3P6sqtGHAxUAp2YCHfHzJL4QyvcEegUIBBC_Ag",
        "description": "Surrounded by local businesses and markets, this low-key hotel is 6 km from Agartala railway station and a 14-minute walk from the Tripura Government Museum, set in a former palace. It's 54 km from the Tripura Sundari Temple, a renowned Hindu shrine dating from the 16th century.<br/>Cosy, modest rooms are equipped with free Wi-Fi, flat-screen TVs and air conditioning. All feature wet rooms. Airy upgraded rooms add sitting areas; some offer armchairs and sofas, as well as minifridges. Room service is available 24 hours.<br/>The reception desk is open 24 hours, and there's a seating area in the lobby. Parking is available. There\u2019s also a generator.",
        "address": "54, Central Rd, Santipara, Dhaleswar, Agartala, Tripura 799001",
        "phone": "0381 238 4530",
        "amenities": {
            "Internet": [
                "Wi-Fifree"
            ],
            "Services": [
                "Front desk24 hour",
                "Full-service laundry"
            ],
            "Pools": [
                "Pool",
                "No hot tub"
            ],
            "Wellness": [
                "No fitness center",
                "No spa"
            ],
            "Rooms": [
                "Air conditioning"
            ],
            "Food & drink": [
                "Room service",
                "Breakfastfree"
            ],
            "Children": [
                "Kid-friendly"
            ],
            "Parking & transportation": [
                "Transfer",
                "Local shuttle"
            ],
            "Pets": [
                "No pets"
            ]
        }
    }
]